piri_cli/__init__.py
piri_cli/cli.py
piri_cli/common.py
piri_cli-2.1.0.dist-info/entry_points.txt
piri_cli-2.1.0.dist-info/LICENSE
piri_cli-2.1.0.dist-info/WHEEL
piri_cli-2.1.0.dist-info/METADATA
piri_cli-2.1.0.dist-info/RECORD
