Metadata-Version: 2.1
Name: piri-cli
Version: 2.1.0
Summary: Piri Json Transformer CLI
Author: Thomas Borgen
Author-email: thomas@borgenit.no
Requires-Python: >=3.6,<4.0
Classifier: Programming Language :: Python :: 3
Classifier: Programming Language :: Python :: 3.6
Classifier: Programming Language :: Python :: 3.7
Classifier: Programming Language :: Python :: 3.8
Requires-Dist: piri (>=2.0.0,<3.0.0)
Requires-Dist: returns (>=0.14.0,<0.15.0)
Requires-Dist: simplejson (>=3.17.2,<4.0.0)
Requires-Dist: typing_extensions (>=3.7.4,<4.0.0)
